libopensesame/__init__.py
libopensesame/base_python_workspace.py
libopensesame/base_response_item.py
libopensesame/cistr.py
libopensesame/debug.py
libopensesame/exceptions.py
libopensesame/experiment.py
libopensesame/feedback.py
libopensesame/file_pool_store.py
libopensesame/generic_response.py
libopensesame/heartbeat.py
libopensesame/inline_script.py
libopensesame/item.py
libopensesame/item_stack.py
libopensesame/item_store.py
libopensesame/keyboard_response.py
libopensesame/logger.py
libopensesame/loop.py
libopensesame/metadata.py
libopensesame/misc.py
libopensesame/mouse_response.py
libopensesame/oslogging.py
libopensesame/plugins.py
libopensesame/py3compat.py
libopensesame/python_workspace.py
libopensesame/python_workspace_api.py
libopensesame/regexp.py
libopensesame/response_store.py
libopensesame/sampler.py
libopensesame/sequence.py
libopensesame/sketchpad.py
libopensesame/syntax.py
libopensesame/synth.py
libopensesame/type_check.py
libopensesame/var_store.py
libopensesame/osexpfile/__init__.py
libopensesame/osexpfile/_osexpbase.py
libopensesame/osexpfile/_osexpreader.py
libopensesame/osexpfile/_osexpwriter.py
libopensesame/sketchpad_elements/__init__.py
libopensesame/sketchpad_elements/_arrow.py
libopensesame/sketchpad_elements/_base_element.py
libopensesame/sketchpad_elements/_circle.py
libopensesame/sketchpad_elements/_ellipse.py
libopensesame/sketchpad_elements/_fixdot.py
libopensesame/sketchpad_elements/_gabor.py
libopensesame/sketchpad_elements/_image.py
libopensesame/sketchpad_elements/_line.py
libopensesame/sketchpad_elements/_noise.py
libopensesame/sketchpad_elements/_rect.py
libopensesame/sketchpad_elements/_textline.py
libopensesame/widgets/__init__.py
libopensesame/widgets/_button.py
libopensesame/widgets/_checkbox.py
libopensesame/widgets/_form.py
libopensesame/widgets/_image.py
libopensesame/widgets/_image_button.py
libopensesame/widgets/_label.py
libopensesame/widgets/_rating_scale.py
libopensesame/widgets/_text_input.py
python_opensesame-3.3.14.dist-info/COPYING
python_opensesame-3.3.14.dist-info/METADATA
python_opensesame-3.3.14.dist-info/WHEEL
python_opensesame-3.3.14.dist-info/entry_points.txt
python_opensesame-3.3.14.dist-info/top_level.txt
python_opensesame-3.3.14.dist-info/RECORD
