Metadata-Version: 2.1
Name: python-opensesame
Version: 3.3.14
Summary: A graphical experiment builder for the social sciences
Home-page: http://osdoc.cogsci.nl/
Author: Sebastiaan Mathot
Author-email: s.mathot@cogsci.nl
Classifier: Development Status :: 4 - Beta
Classifier: Intended Audience :: Science/Research
Classifier: Topic :: Scientific/Engineering
Classifier: License :: OSI Approved :: GNU General Public License v3 (GPLv3)
Classifier: Programming Language :: Python :: 2
Classifier: Programming Language :: Python :: 3
License-File: COPYING
Requires-Dist: pyqode3.python
Requires-Dist: python-qdatamatrix
Requires-Dist: python-pseudorandom
Requires-Dist: python-qnotifications
Requires-Dist: python-fileinspector
Requires-Dist: PyYAML
Requires-Dist: webcolors
